eth0/__init__.py
eth0/address.py
eth0/sign.py
eth0-0.1.3.dist-info/LICENSE
eth0-0.1.3.dist-info/METADATA
eth0-0.1.3.dist-info/WHEEL
eth0-0.1.3.dist-info/entry_points.txt
eth0-0.1.3.dist-info/top_level.txt
eth0-0.1.3.dist-info/RECORD
