Metadata-Version: 2.1
Name: eth0
Version: 0.1.3
Summary: Ethereum toolkit
Author-email: Jarkko Sakkinen <jarkko.sakkinen@iki.fi>
License: Copyright (c) 2024 Jarkko Sakkinen
Project-URL: Homepage, https://codeberg.org/jarkko/eth0
Project-URL: Repository, https://codeberg.org/jarkko/eth0.git
Project-URL: Issues, https://codeberg.org/jarkko/eth0/issues
License-File: LICENSE
Requires-Dist: eth-account
Requires-Dist: eth-keys
